bayesianflow_for_chem/__init__.py
bayesianflow_for_chem/cli.py
bayesianflow_for_chem/data.py
bayesianflow_for_chem/model.py
bayesianflow_for_chem/scorer.py
bayesianflow_for_chem/spectra.py
bayesianflow_for_chem/tool.py
bayesianflow_for_chem/train.py
bayesianflow_for_chem/_data/vocab.txt
bayesianflow_for_chem-2.4.3.dist-info/licenses/LICENSE
bayesianflow_for_chem-2.4.3.dist-info/METADATA
bayesianflow_for_chem-2.4.3.dist-info/WHEEL
bayesianflow_for_chem-2.4.3.dist-info/entry_points.txt
bayesianflow_for_chem-2.4.3.dist-info/top_level.txt
bayesianflow_for_chem-2.4.3.dist-info/RECORD
