Metadata-Version: 2.4
Name: bayesianflow_for_chem
Version: 2.4.3
Summary: Bayesian flow network framework for Chemistry
Home-page: https://augus1999.github.io/bayesian-flow-network-for-chemistry/
Author: Nianze A. Tao
Author-email: tao-nianze@hiroshima-u.ac.jp
License: AGPL-3.0-or-later
Project-URL: Source, https://github.com/Augus1999/bayesian-flow-network-for-chemistry
Keywords: Chemistry,CLM,ChemBFN
Classifier: Development Status :: 5 - Production/Stable
Classifier: Intended Audience :: Science/Research
Classifier: Natural Language :: English
Classifier: Programming Language :: Python :: 3
Classifier: Programming Language :: Python :: 3.11
Classifier: Programming Language :: Python :: 3.12
Classifier: Programming Language :: Python :: 3.13
Classifier: Programming Language :: Python :: 3.14
Classifier: Topic :: Scientific/Engineering :: Chemistry
Classifier: Topic :: Scientific/Engineering :: Artificial Intelligence
Requires-Python: >=3.11
License-File: LICENSE
Requires-Dist: rdkit>=2025.3.5
Requires-Dist: torch>=2.8.0
Requires-Dist: torchao>=0.12
Requires-Dist: numpy>=2.3.2
Requires-Dist: scipy>=1.16.1
Requires-Dist: lightning>=2.5.3
Requires-Dist: scikit-learn>=1.7.1
Requires-Dist: colorama>=0.4.6; platform_system == "Windows"
Dynamic: author
Dynamic: author-email
Dynamic: classifier
Dynamic: description
Dynamic: description-content-type
Dynamic: home-page
Dynamic: keywords
Dynamic: license
Dynamic: license-file
Dynamic: project-url
Dynamic: requires-dist
Dynamic: requires-python
Dynamic: summary
